pysnoo/__init__.py
pysnoo/auth_session.py
pysnoo/const.py
pysnoo/models.py
pysnoo/oauth2_session.py
pysnoo/pubnub.py
pysnoo/snoo.py
pysnoo-0.1.2.data/scripts/snoo
pysnoo-0.1.2.dist-info/LICENSE
pysnoo-0.1.2.dist-info/METADATA
pysnoo-0.1.2.dist-info/WHEEL
pysnoo-0.1.2.dist-info/top_level.txt
pysnoo-0.1.2.dist-info/RECORD
