Metadata-Version: 2.1
Name: pysnoo
Version: 0.1.2
Summary: A Python library and CLI to communicate with the Snoo Smart Baby Sleeper and Bassinet from Happiest Baby
Home-page: https://github.com/rado0x54/pysnoo
Author: Martin Riedel
Author-email: web@riedel-it.de
License: MIT
Keywords: baby,snoo,home automation
Platform: UNKNOWN
Classifier: Development Status :: 4 - Beta
Classifier: Environment :: Other Environment
Classifier: Intended Audience :: Developers
Classifier: License :: OSI Approved :: MIT License
Classifier: Operating System :: OS Independent
Classifier: Programming Language :: Python
Classifier: Programming Language :: Python :: 3.7
Classifier: Programming Language :: Python :: 3.8
Classifier: Programming Language :: Python :: 3.9
Classifier: Topic :: Home Automation
Classifier: Topic :: Software Development :: Libraries :: Python Modules
Requires-Python: >=3.7, <4
Requires-Dist: oauthlib
Requires-Dist: aiohttp
Requires-Dist: pubnub (>=5.0.0)
